langchain_g4f/G4FLLM.py
langchain_g4f/__init__.py
langchain_g4f-0.1.dist-info/LICENSE
langchain_g4f-0.1.dist-info/METADATA
langchain_g4f-0.1.dist-info/WHEEL
langchain_g4f-0.1.dist-info/top_level.txt
langchain_g4f-0.1.dist-info/RECORD
