Metadata-Version: 2.1
Name: langchain-g4f
Version: 0.1
Summary: LangChain gpt4free is an open-source project that assists in building applications using LLM (Large Language Models) and provides free access to GPT4/3.5.
Home-page: https://github.com/AlexanderKorataev/langchain-gpt4free
Author: Alexander
Author-email: alexandkorataev@gmain.com
License: MIT License
Classifier: Programming Language :: Python :: 3
Classifier: License :: OSI Approved :: MIT License
Classifier: Operating System :: OS Independent
Requires-Python: >=3.10
License-File: LICENSE
Requires-Dist: aiofiles ==23.2.1
Requires-Dist: aiohttp ==3.8.6
Requires-Dist: aiosignal ==1.3.1
Requires-Dist: annotated-types ==0.6.0
Requires-Dist: anyio ==3.7.1
Requires-Dist: async-timeout ==4.0.3
Requires-Dist: attrs ==23.1.0
Requires-Dist: blinker ==1.6.3
Requires-Dist: Brotli ==1.1.0
Requires-Dist: browser-cookie3 ==0.19.1
Requires-Dist: certifi ==2023.7.22
Requires-Dist: cffi ==1.16.0
Requires-Dist: charset-normalizer ==3.3.1
Requires-Dist: click ==8.1.7
Requires-Dist: cryptography ==41.0.5
Requires-Dist: curl-cffi ==0.5.9
Requires-Dist: dataclasses-json ==0.6.1
Requires-Dist: docutils ==0.20.1
Requires-Dist: duckduckgo-search ==3.9.3
Requires-Dist: Flask ==3.0.0
Requires-Dist: Flask-Cors ==4.0.0
Requires-Dist: frozenlist ==1.4.0
Requires-Dist: g4f ==0.1.7.6
Requires-Dist: greenlet ==3.0.0
Requires-Dist: h11 ==0.14.0
Requires-Dist: h2 ==4.1.0
Requires-Dist: hpack ==4.0.0
Requires-Dist: httpcore ==0.18.0
Requires-Dist: httpx ==0.25.0
Requires-Dist: hyperframe ==6.0.1
Requires-Dist: idna ==3.4
Requires-Dist: importlib-metadata ==6.8.0
Requires-Dist: itsdangerous ==2.1.2
Requires-Dist: jaraco.classes ==3.3.0
Requires-Dist: jeepney ==0.8.0
Requires-Dist: Jinja2 ==3.1.2
Requires-Dist: Js2Py ==0.74
Requires-Dist: jsonpatch ==1.33
Requires-Dist: jsonpointer ==2.4
Requires-Dist: keyring ==24.2.0
Requires-Dist: langchain ==0.0.321
Requires-Dist: langsmith ==0.0.49
Requires-Dist: loguru ==0.7.2
Requires-Dist: lxml ==4.9.3
Requires-Dist: lz4 ==4.3.2
Requires-Dist: markdown-it-py ==3.0.0
Requires-Dist: MarkupSafe ==2.1.3
Requires-Dist: marshmallow ==3.20.1
Requires-Dist: mdurl ==0.1.2
Requires-Dist: more-itertools ==10.1.0
Requires-Dist: multidict ==6.0.4
Requires-Dist: mypy-extensions ==1.0.0
Requires-Dist: nest-asyncio ==1.5.8
Requires-Dist: nh3 ==0.2.14
Requires-Dist: numpy ==1.26.1
Requires-Dist: packaging ==23.2
Requires-Dist: Pillow ==10.1.0
Requires-Dist: pkginfo ==1.9.6
Requires-Dist: platformdirs ==3.11.0
Requires-Dist: pycparser ==2.21
Requires-Dist: pycryptodome ==3.19.0
Requires-Dist: pycryptodomex ==3.19.0
Requires-Dist: pydantic ==2.4.2
Requires-Dist: pydantic-core ==2.10.1
Requires-Dist: PyExecJS ==1.5.1
Requires-Dist: Pygments ==2.16.1
Requires-Dist: pyjsparser ==2.7.1
Requires-Dist: PyYAML ==6.0.1
Requires-Dist: readme-renderer ==42.0
Requires-Dist: regex ==2023.10.3
Requires-Dist: requests ==2.31.0
Requires-Dist: requests-toolbelt ==1.0.0
Requires-Dist: rfc3986 ==2.0.0
Requires-Dist: rich ==13.6.0
Requires-Dist: SecretStorage ==3.3.3
Requires-Dist: six ==1.16.0
Requires-Dist: sniffio ==1.3.0
Requires-Dist: socksio ==1.0.0
Requires-Dist: SQLAlchemy ==2.0.22
Requires-Dist: tenacity ==8.2.3
Requires-Dist: tiktoken ==0.5.1
Requires-Dist: twine ==4.0.2
Requires-Dist: typing-inspect ==0.9.0
Requires-Dist: typing-extensions ==4.8.0
Requires-Dist: tzlocal ==5.2
Requires-Dist: urllib3 ==2.0.7
Requires-Dist: waitress ==2.1.2
Requires-Dist: websockets ==12.0
Requires-Dist: Werkzeug ==3.0.0
Requires-Dist: yarl ==1.9.2
Requires-Dist: zipp ==3.17.0
